LICENSE.txt
README.rst
requirements.txt
setup.cfg
setup.py
test-requirements.txt
tox.ini
doc/Makefile
doc/make.bat
doc/source/conf.py
doc/source/index.rst
etc/inventory.ini
etc/netsurvey.config
net_survey/__init__.py
net_survey/interfaces.py
net_survey/survey.py
net_survey.egg-info/PKG-INFO
net_survey.egg-info/SOURCES.txt
net_survey.egg-info/dependency_links.txt
net_survey.egg-info/entry_points.txt
net_survey.egg-info/pbr.json
net_survey.egg-info/requires.txt
net_survey.egg-info/top_level.txt
net_survey/client/__init__.py
net_survey/client/client.py
net_survey/client/scanner.py
net_survey/server/__init__.py
net_survey/server/api.py
net_survey/server/server.py
net_survey/tests/__init__.py
net_survey/tests/base.py
releasenotes/notes/.placeholder
releasenotes/source/README.rst
releasenotes/source/conf.py
releasenotes/source/index.rst
releasenotes/source/unreleased.rst
releasenotes/source/_static/.placeholder
releasenotes/source/_templates/.placeholder