Metadata-Version: 1.1
Name: net-survey
Version: 0.0.2
Summary: Installation Network Survey
Home-page: https://github.com/stajkowski/net-survey
Author: Brian Stajkowski
Author-email: stajkowski100@gmail.com
License: Apache
Keywords: network survey
Platform: UNKNOWN
Classifier: Development Status :: 3 - Alpha
Classifier: Intended Audience :: Developers
Classifier: Topic :: Software Development :: Build Tools
Classifier: License :: OSI Approved :: MIT License
Classifier: Programming Language :: Python :: 2
Classifier: Programming Language :: Python :: 2.6
Classifier: Programming Language :: Python :: 2.7
Classifier: Programming Language :: Python :: 3
Classifier: Programming Language :: Python :: 3.3
Classifier: Programming Language :: Python :: 3.4
Classifier: Programming Language :: Python :: 3.5
